diamond_registry/__init__.py
diamond_registry/diamond_registry.py
diamond_registry-0.1.2.dist-info/METADATA
diamond_registry-0.1.2.dist-info/WHEEL
diamond_registry-0.1.2.dist-info/top_level.txt
diamond_registry-0.1.2.dist-info/RECORD
