Metadata-Version: 2.1
Name: diamond-registry
Version: 0.1.2
Summary: Diamond registry and price estimation system
Home-page: https://gitlab.com/data-revenue/code-challenge/submissions/diamonds-louise
Author: Louise Poole
Author-email: louisecarmenpoole@gmail.com
License: MIT
Platform: UNKNOWN
Requires-Dist: mysql-connector-python
